reflex_chat/__init__.py
reflex_chat/api.py
reflex_chat/chat.py
reflex_chat/components.py
reflex_chat-0.0.1.dist-info/METADATA
reflex_chat-0.0.1.dist-info/WHEEL
reflex_chat-0.0.1.dist-info/top_level.txt
reflex_chat-0.0.1.dist-info/RECORD
