Metadata-Version: 2.1
Name: reflex-chat
Version: 0.0.1
Summary: Reflex custom component chat
Author-email: Nikhil Rao <nikhil@reflex.dev>
License: Apache-2.0
Project-URL: homepage, https://github.com/picklelo/reflex-chat
Project-URL: source, https://github.com/picklelo/reflex-chat
Keywords: reflex,reflex-custom-components
Classifier: Development Status :: 4 - Beta
Requires-Python: >=3.8
Requires-Dist: reflex >=0.4.7
Provides-Extra: dev
Requires-Dist: build ; extra == 'dev'
Requires-Dist: twine ; extra == 'dev'
